{"last_tab":"","logo_type":"logo_image","inventory_logo_text":"Inventory WP Theme","inventory_logo_image":{"url":"http:\/\/inventory.jeweltheme.com\/wp-content\/themes\/inventory\/images\/logo3.png","id":"","height":"","width":"","thumbnail":""},"top_bar":"show","language_settings":"show","language":["en, EN, ltr","ar, AR, rtl","br, BR, ltr","fr, FR, ltr","de, DE, ltr","id, ID, ltr","ja, JA, ltr","sr, SR, ltr"],"enable_preloader":"disable","scroll_top":"enable","page_comments":"1","listing_style":"style1","listing_style1":{"url":"http:\/\/inventory.jeweltheme.com\/wp-content\/themes\/inventory\/images\/listing\/style1.jpg","id":"","height":"","width":"","thumbnail":""},"listing_style2":{"url":"http:\/\/inventory.jeweltheme.com\/wp-content\/themes\/inventory\/images\/listing\/style2.jpg","id":"","height":"","width":"","thumbnail":""},"listing_style3":{"url":"http:\/\/inventory.jeweltheme.com\/wp-content\/themes\/inventory\/images\/listing\/style1.jpg","id":"","height":"","width":"","thumbnail":""},"listing_style4":{"url":"http:\/\/inventory.jeweltheme.com\/wp-content\/themes\/inventory\/images\/listing\/style2.jpg","id":"","height":"","width":"","thumbnail":""},"keywords_on_tax":"hide","mapbox_token":"","mapbox_style":"1","google_maps_api_key":"","header_color":"defualt","top_header_bg":"","navbar_bg_color":"","navbar_text_color":"","navbar_link_hover_color":"","navbar_dropdown_bg_color":"","navbar_dropdown_text_color":"","navbar_dropdown_hover_color":"","footer_bg":{"url":"http:\/\/inventory.jeweltheme.com\/wp-content\/themes\/inventory\/images\/world-map.jpg","id":"","height":"","width":"","thumbnail":""},"copyright_text":"&#169; Inventory 2017 | Developed By Developed By <a href=\" https:\/\/jeweltheme.com\"> Jewel Theme<\/a> Designed By <a href=\"http:\/\/themeforest.net\/user\/bigpsfan\">bigpsfan<\/a>","redux-backup":"1"}